robyn_rate_limits/__init__.py
robyn_rate_limits/in_memory.py
robyn_rate_limits/protocols.py
robyn_rate_limits/py.typed
robyn_rate_limits/rate_limiter.py
robyn_rate_limits/redis.py
robyn_rate_limits-0.4.0.dist-info/METADATA
robyn_rate_limits-0.4.0.dist-info/WHEEL
robyn_rate_limits-0.4.0.dist-info/entry_points.txt
robyn_rate_limits-0.4.0.dist-info/licenses/LICENSE
robyn_rate_limits-0.4.0.dist-info/RECORD
