Metadata-Version: 2.4
Name: robyn-rate-limits
Version: 0.4.0
Author-email: IdoKendo <ryuusuke@gmail.com>
License-File: LICENSE
Requires-Python: >=3.9
Requires-Dist: cachetools>=5
Requires-Dist: redis>=5; extra == 'redis'
Requires-Dist: robyn>=0.72
Provides-Extra: redis
Requires-Dist: redis>=5; extra == 'redis'
